{
    "_ansible_facts_gathered": true,
    "all_ipv4_addresses": [
        "10.42.2.121"
    ],
    "all_ipv6_addresses": [
        "fe80::9c0b:ceff:fe54:4d40"
    ],
    "ansible_local": {},
    "apparmor": {
        "status": "disabled"
    },
    "architecture": "x86_64",
    "bios_date": "04/01/2014",
    "bios_vendor": "SeaBIOS",
    "bios_version": "1.16.3-2.el9",
    "board_asset_tag": "NA",
    "board_name": "RHEL",
    "board_serial": "NA",
    "board_vendor": "Red Hat",
    "board_version": "RHEL-9.4.0 PC (Q35 + ICH9, 2009)",
    "chassis_asset_tag": "NA",
    "chassis_serial": "NA",
    "chassis_vendor": "Red Hat",
    "chassis_version": "RHEL-9.4.0 PC (Q35 + ICH9, 2009)",
    "cmdline": {
        "BOOT_IMAGE": "(hd0,gpt2)/boot/vmlinuz-6.12.0-39.el10.x86_64",
        "console": "ttyS0,115200n8",
        "crashkernel": "1G-4G:192M,4G-64G:256M,64G-:512M",
        "no_timer_check": true,
        "ro": true,
        "root": "UUID=6b954e15-c908-4267-af94-914517f663e0"
    },
    "date_time": {
        "date": "2025-01-28",
        "day": "28",
        "epoch": "1738065507",
        "epoch_int": "1738065507",
        "hour": "06",
        "iso8601": "2025-01-28T11:58:27Z",
        "iso8601_basic": "20250128T065827569407",
        "iso8601_basic_short": "20250128T065827",
        "iso8601_micro": "2025-01-28T11:58:27.569407Z",
        "minute": "58",
        "month": "01",
        "second": "27",
        "time": "06:58:27",
        "tz": "EST",
        "tz_dst": "EDT",
        "tz_offset": "-0500",
        "weekday": "Tuesday",
        "weekday_number": "2",
        "weeknumber": "04",
        "year": "2025"
    },
    "default_ipv4": {
        "address": "10.42.2.121",
        "alias": "enp1s0",
        "broadcast": "",
        "gateway": "169.254.1.1",
        "interface": "enp1s0",
        "macaddress": "9e:0b:ce:54:4d:40",
        "mtu": 1450,
        "netmask": "255.255.255.255",
        "network": "10.42.2.121",
        "prefix": "32",
        "type": "ether"
    },
    "default_ipv6": {},
    "device_links": {
        "ids": {},
        "labels": {
            "vdb": [
                "cidata"
            ]
        },
        "masters": {},
        "uuids": {
            "vda2": [
                "6b954e15-c908-4267-af94-914517f663e0"
            ],
            "vdb": [
                "2025-01-28-11-57-40-00"
            ]
        }
    },
    "devices": {
        "vda": {
            "holders": [],
            "host": "",
            "links": {
                "ids": [],
                "labels": [],
                "masters": [],
                "uuids": []
            },
            "model": null,
            "partitions": {
                "vda1": {
                    "holders": [],
                    "links": {
                        "ids": [],
                        "labels": [],
                        "masters": [],
                        "uuids": []
                    },
                    "sectors": "2048",
                    "sectorsize": 512,
                    "size": "1.00 MB",
                    "start": "2048",
                    "uuid": null
                },
                "vda2": {
                    "holders": [],
                    "links": {
                        "ids": [],
                        "labels": [],
                        "masters": [],
                        "uuids": [
                            "6b954e15-c908-4267-af94-914517f663e0"
                        ]
                    },
                    "sectors": "20967391",
                    "sectorsize": 512,
                    "size": "10.00 GB",
                    "start": "4096",
                    "uuid": "6b954e15-c908-4267-af94-914517f663e0"
                }
            },
            "removable": "0",
            "rotational": "1",
            "sas_address": null,
            "sas_device_handle": null,
            "scheduler_mode": "mq-deadline",
            "sectors": "20971520",
            "sectorsize": "512",
            "size": "10.00 GB",
            "support_discard": "512",
            "vendor": "0x1af4",
            "virtual": 1
        },
        "vdb": {
            "holders": [],
            "host": "",
            "links": {
                "ids": [],
                "labels": [
                    "cidata"
                ],
                "masters": [],
                "uuids": [
                    "2025-01-28-11-57-40-00"
                ]
            },
            "model": null,
            "partitions": {},
            "removable": "0",
            "rotational": "1",
            "sas_address": null,
            "sas_device_handle": null,
            "scheduler_mode": "mq-deadline",
            "sectors": "2048",
            "sectorsize": "512",
            "size": "1.00 MB",
            "support_discard": "512",
            "vendor": "0x1af4",
            "virtual": 1
        },
        "vdc": {
            "holders": [],
            "host": "",
            "links": {
                "ids": [],
                "labels": [],
                "masters": [],
                "uuids": []
            },
            "model": null,
            "partitions": {},
            "removable": "0",
            "rotational": "1",
            "sas_address": null,
            "sas_device_handle": null,
            "scheduler_mode": "mq-deadline",
            "sectors": "4194304",
            "sectorsize": "512",
            "size": "2.00 GB",
            "support_discard": "512",
            "vendor": "0x1af4",
            "virtual": 1
        }
    },
    "discovered_interpreter_python": "/usr/bin/python3",
    "distribution": "CentOS",
    "distribution_file_parsed": true,
    "distribution_file_path": "/etc/centos-release",
    "distribution_file_variety": "CentOS",
    "distribution_major_version": "10",
    "distribution_release": "Stream",
    "distribution_version": "10",
    "dns": {
        "nameservers": [
            "10.43.0.10"
        ],
        "search": [
            "molecule.svc.cluster.local",
            "svc.cluster.local",
            "cluster.local",
            "h.c6d.xyz"
        ]
    },
    "domain": "molecule.svc.cluster.local",
    "effective_group_id": 1000,
    "effective_user_id": 1000,
    "enp1s0": {
        "active": true,
        "device": "enp1s0",
        "features": {
            "esp_hw_offload": "off [fixed]",
            "esp_tx_csum_hw_offload": "off [fixed]",
            "generic_receive_offload": "on",
            "generic_segmentation_offload": "on",
            "highdma": "on [fixed]",
            "hsr_dup_offload": "off [fixed]",
            "hsr_fwd_offload": "off [fixed]",
            "hsr_tag_ins_offload": "off [fixed]",
            "hsr_tag_rm_offload": "off [fixed]",
            "hw_tc_offload": "off [fixed]",
            "l2_fwd_offload": "off [fixed]",
            "large_receive_offload": "off [fixed]",
            "loopback": "off [fixed]",
            "macsec_hw_offload": "off [fixed]",
            "ntuple_filters": "off [fixed]",
            "receive_hashing": "off [fixed]",
            "rx_all": "off [fixed]",
            "rx_checksumming": "on [fixed]",
            "rx_fcs": "off [fixed]",
            "rx_gro_hw": "on",
            "rx_gro_list": "off",
            "rx_udp_gro_forwarding": "off",
            "rx_udp_tunnel_port_offload": "off [fixed]",
            "rx_vlan_filter": "on [fixed]",
            "rx_vlan_offload": "off [fixed]",
            "rx_vlan_stag_filter": "off [fixed]",
            "rx_vlan_stag_hw_parse": "off [fixed]",
            "scatter_gather": "on",
            "tcp_segmentation_offload": "on",
            "tls_hw_record": "off [fixed]",
            "tls_hw_rx_offload": "off [fixed]",
            "tls_hw_tx_offload": "off [fixed]",
            "tx_checksum_fcoe_crc": "off [fixed]",
            "tx_checksum_ip_generic": "on",
            "tx_checksum_ipv4": "off [fixed]",
            "tx_checksum_ipv6": "off [fixed]",
            "tx_checksum_sctp": "off [fixed]",
            "tx_checksumming": "on",
            "tx_esp_segmentation": "off [fixed]",
            "tx_fcoe_segmentation": "off [fixed]",
            "tx_gre_csum_segmentation": "off [fixed]",
            "tx_gre_segmentation": "off [fixed]",
            "tx_gso_list": "off [fixed]",
            "tx_gso_partial": "off [fixed]",
            "tx_gso_robust": "on [fixed]",
            "tx_ipxip4_segmentation": "off [fixed]",
            "tx_ipxip6_segmentation": "off [fixed]",
            "tx_nocache_copy": "off",
            "tx_scatter_gather": "on",
            "tx_scatter_gather_fraglist": "off [fixed]",
            "tx_sctp_segmentation": "off [fixed]",
            "tx_tcp6_segmentation": "on",
            "tx_tcp_ecn_segmentation": "on",
            "tx_tcp_mangleid_segmentation": "off",
            "tx_tcp_segmentation": "on",
            "tx_tunnel_remcsum_segmentation": "off [fixed]",
            "tx_udp_segmentation": "off [fixed]",
            "tx_udp_tnl_csum_segmentation": "off [fixed]",
            "tx_udp_tnl_segmentation": "off [fixed]",
            "tx_vlan_offload": "off [fixed]",
            "tx_vlan_stag_hw_insert": "off [fixed]",
            "vlan_challenged": "off [fixed]"
        },
        "hw_timestamp_filters": [],
        "ipv4": {
            "address": "10.42.2.121",
            "broadcast": "",
            "netmask": "255.255.255.255",
            "network": "10.42.2.121",
            "prefix": "32"
        },
        "ipv6": [
            {
                "address": "fe80::9c0b:ceff:fe54:4d40",
                "prefix": "64",
                "scope": "link"
            }
        ],
        "macaddress": "9e:0b:ce:54:4d:40",
        "module": "virtio_net",
        "mtu": 1450,
        "pciid": "virtio0",
        "promisc": false,
        "speed": -1,
        "timestamping": [],
        "type": "ether"
    },
    "env": {
        "DBUS_SESSION_BUS_ADDRESS": "unix:path=/run/user/1000/bus",
        "DEBUGINFOD_URLS": "https://debuginfod.centos.org/ ",
        "HOME": "/home/molecule",
        "LANG": "en_US.UTF-8",
        "LESSOPEN": "||/usr/bin/lesspipe.sh %s",
        "LOGNAME": "molecule",
        "LS_COLORS": "rs=0:di=01;34:ln=01;36:mh=00:pi=40;33:so=01;35:do=01;35:bd=40;33;01:cd=40;33;01:or=40;31;01:mi=01;37;41:su=37;41:sg=30;43:ca=00:tw=30;42:ow=34;42:st=37;44:ex=01;32:*.7z=01;31:*.ace=01;31:*.alz=01;31:*.apk=01;31:*.arc=01;31:*.arj=01;31:*.bz=01;31:*.bz2=01;31:*.cab=01;31:*.cpio=01;31:*.crate=01;31:*.deb=01;31:*.drpm=01;31:*.dwm=01;31:*.dz=01;31:*.ear=01;31:*.egg=01;31:*.esd=01;31:*.gz=01;31:*.jar=01;31:*.lha=01;31:*.lrz=01;31:*.lz=01;31:*.lz4=01;31:*.lzh=01;31:*.lzma=01;31:*.lzo=01;31:*.pyz=01;31:*.rar=01;31:*.rpm=01;31:*.rz=01;31:*.sar=01;31:*.swm=01;31:*.t7z=01;31:*.tar=01;31:*.taz=01;31:*.tbz=01;31:*.tbz2=01;31:*.tgz=01;31:*.tlz=01;31:*.txz=01;31:*.tz=01;31:*.tzo=01;31:*.tzst=01;31:*.udeb=01;31:*.war=01;31:*.whl=01;31:*.wim=01;31:*.xz=01;31:*.z=01;31:*.zip=01;31:*.zoo=01;31:*.zst=01;31:*.avif=01;35:*.jpg=01;35:*.jpeg=01;35:*.mjpg=01;35:*.mjpeg=01;35:*.gif=01;35:*.bmp=01;35:*.pbm=01;35:*.pgm=01;35:*.ppm=01;35:*.tga=01;35:*.xbm=01;35:*.xpm=01;35:*.tif=01;35:*.tiff=01;35:*.png=01;35:*.svg=01;35:*.svgz=01;35:*.mng=01;35:*.pcx=01;35:*.mov=01;35:*.mpg=01;35:*.mpeg=01;35:*.m2v=01;35:*.mkv=01;35:*.webm=01;35:*.webp=01;35:*.ogm=01;35:*.mp4=01;35:*.m4v=01;35:*.mp4v=01;35:*.vob=01;35:*.qt=01;35:*.nuv=01;35:*.wmv=01;35:*.asf=01;35:*.rm=01;35:*.rmvb=01;35:*.flc=01;35:*.avi=01;35:*.fli=01;35:*.flv=01;35:*.gl=01;35:*.dl=01;35:*.xcf=01;35:*.xwd=01;35:*.yuv=01;35:*.cgm=01;35:*.emf=01;35:*.ogv=01;35:*.ogx=01;35:*.aac=01;36:*.au=01;36:*.flac=01;36:*.m4a=01;36:*.mid=01;36:*.midi=01;36:*.mka=01;36:*.mp3=01;36:*.mpc=01;36:*.ogg=01;36:*.ra=01;36:*.wav=01;36:*.oga=01;36:*.opus=01;36:*.spx=01;36:*.xspf=01;36:*~=00;90:*#=00;90:*.bak=00;90:*.crdownload=00;90:*.dpkg-dist=00;90:*.dpkg-new=00;90:*.dpkg-old=00;90:*.dpkg-tmp=00;90:*.old=00;90:*.orig=00;90:*.part=00;90:*.rej=00;90:*.rpmnew=00;90:*.rpmorig=00;90:*.rpmsave=00;90:*.swp=00;90:*.tmp=00;90:*.ucf-dist=00;90:*.ucf-new=00;90:*.ucf-old=00;90:",
        "MOTD_SHOWN": "pam",
        "PATH": "/home/molecule/.local/bin:/home/molecule/bin:/usr/local/bin:/usr/bin:/usr/local/sbin:/usr/sbin",
        "PWD": "/home/molecule",
        "SELINUX_LEVEL_REQUESTED": "",
        "SELINUX_ROLE_REQUESTED": "",
        "SELINUX_USE_CURRENT_RANGE": "",
        "SHELL": "/bin/bash",
        "SHLVL": "1",
        "SSH_CLIENT": "10.42.0.0 49444 22",
        "SSH_CONNECTION": "10.42.0.0 49444 10.42.2.121 22",
        "SSH_TTY": "/dev/pts/0",
        "TERM": "xterm-256color",
        "USER": "molecule",
        "XDG_RUNTIME_DIR": "/run/user/1000",
        "XDG_SESSION_CLASS": "user",
        "XDG_SESSION_ID": "1",
        "XDG_SESSION_TYPE": "tty",
        "_": "/usr/bin/python3"
    },
    "fibre_channel_wwn": [],
    "fips": false,
    "form_factor": "Other",
    "fqdn": "facts-centos10.molecule.svc.cluster.local",
    "gather_subset": [
        "all"
    ],
    "hostname": "facts-centos10",
    "hostnqn": "nqn.2014-08.org.nvmexpress:uuid:66384fb6-45f6-46fb-ba32-35eeaa57cd2a",
    "interfaces": [
        "lo",
        "enp1s0"
    ],
    "is_chroot": false,
    "iscsi_iqn": "",
    "kernel": "6.12.0-39.el10.x86_64",
    "kernel_version": "#1 SMP PREEMPT_DYNAMIC Thu Jan  9 16:11:58 UTC 2025",
    "lo": {
        "active": true,
        "device": "lo",
        "features": {
            "esp_hw_offload": "off [fixed]",
            "esp_tx_csum_hw_offload": "off [fixed]",
            "generic_receive_offload": "on",
            "generic_segmentation_offload": "on",
            "highdma": "on [fixed]",
            "hsr_dup_offload": "off [fixed]",
            "hsr_fwd_offload": "off [fixed]",
            "hsr_tag_ins_offload": "off [fixed]",
            "hsr_tag_rm_offload": "off [fixed]",
            "hw_tc_offload": "off [fixed]",
            "l2_fwd_offload": "off [fixed]",
            "large_receive_offload": "off [fixed]",
            "loopback": "on [fixed]",
            "macsec_hw_offload": "off [fixed]",
            "ntuple_filters": "off [fixed]",
            "receive_hashing": "off [fixed]",
            "rx_all": "off [fixed]",
            "rx_checksumming": "on [fixed]",
            "rx_fcs": "off [fixed]",
            "rx_gro_hw": "off [fixed]",
            "rx_gro_list": "off",
            "rx_udp_gro_forwarding": "off",
            "rx_udp_tunnel_port_offload": "off [fixed]",
            "rx_vlan_filter": "off [fixed]",
            "rx_vlan_offload": "off [fixed]",
            "rx_vlan_stag_filter": "off [fixed]",
            "rx_vlan_stag_hw_parse": "off [fixed]",
            "scatter_gather": "on",
            "tcp_segmentation_offload": "on",
            "tls_hw_record": "off [fixed]",
            "tls_hw_rx_offload": "off [fixed]",
            "tls_hw_tx_offload": "off [fixed]",
            "tx_checksum_fcoe_crc": "off [fixed]",
            "tx_checksum_ip_generic": "on [fixed]",
            "tx_checksum_ipv4": "off [fixed]",
            "tx_checksum_ipv6": "off [fixed]",
            "tx_checksum_sctp": "on [fixed]",
            "tx_checksumming": "on",
            "tx_esp_segmentation": "off [fixed]",
            "tx_fcoe_segmentation": "off [fixed]",
            "tx_gre_csum_segmentation": "off [fixed]",
            "tx_gre_segmentation": "off [fixed]",
            "tx_gso_list": "on",
            "tx_gso_partial": "off [fixed]",
            "tx_gso_robust": "off [fixed]",
            "tx_ipxip4_segmentation": "off [fixed]",
            "tx_ipxip6_segmentation": "off [fixed]",
            "tx_nocache_copy": "off [fixed]",
            "tx_scatter_gather": "on [fixed]",
            "tx_scatter_gather_fraglist": "on [fixed]",
            "tx_sctp_segmentation": "on",
            "tx_tcp6_segmentation": "on",
            "tx_tcp_ecn_segmentation": "on",
            "tx_tcp_mangleid_segmentation": "on",
            "tx_tcp_segmentation": "on",
            "tx_tunnel_remcsum_segmentation": "off [fixed]",
            "tx_udp_segmentation": "on",
            "tx_udp_tnl_csum_segmentation": "off [fixed]",
            "tx_udp_tnl_segmentation": "off [fixed]",
            "tx_vlan_offload": "off [fixed]",
            "tx_vlan_stag_hw_insert": "off [fixed]",
            "vlan_challenged": "on [fixed]"
        },
        "hw_timestamp_filters": [],
        "ipv4": {
            "address": "127.0.0.1",
            "broadcast": "",
            "netmask": "255.0.0.0",
            "network": "127.0.0.0",
            "prefix": "8"
        },
        "ipv6": [
            {
                "address": "::1",
                "prefix": "128",
                "scope": "host"
            }
        ],
        "mtu": 65536,
        "promisc": false,
        "timestamping": [],
        "type": "loopback"
    },
    "loadavg": {
        "15m": 0.02490234375,
        "1m": 0.26025390625,
        "5m": 0.076171875
    },
    "locally_reachable_ips": {
        "ipv4": [
            "10.42.2.121",
            "127.0.0.0/8",
            "127.0.0.1"
        ],
        "ipv6": [
            "::1",
            "fe80::9c0b:ceff:fe54:4d40"
        ]
    },
    "lsb": {},
    "lvm": "N/A",
    "machine": "x86_64",
    "machine_id": "265a20ede31959f4aa67fc0c280a0a4e",
    "memfree_mb": 379,
    "memory_mb": {
        "nocache": {
            "free": 557,
            "used": 205
        },
        "real": {
            "free": 379,
            "total": 762,
            "used": 383
        },
        "swap": {
            "cached": 0,
            "free": 0,
            "total": 0,
            "used": 0
        }
    },
    "memtotal_mb": 762,
    "module_setup": true,
    "mounts": [
        {
            "block_available": 2277742,
            "block_size": 4096,
            "block_total": 2604539,
            "block_used": 326797,
            "device": "/dev/vda2",
            "fstype": "xfs",
            "inode_available": 5205048,
            "inode_total": 5241840,
            "inode_used": 36792,
            "mount": "/",
            "options": "rw,seclabel,relatime,attr2,inode64,logbufs=8,logbsize=32k,noquota",
            "size_available": 9329631232,
            "size_total": 10668191744,
            "uuid": "6b954e15-c908-4267-af94-914517f663e0"
        }
    ],
    "nodename": "facts-centos10",
    "os_family": "RedHat",
    "pkg_mgr": "dnf",
    "proc_cmdline": {
        "BOOT_IMAGE": "(hd0,gpt2)/boot/vmlinuz-6.12.0-39.el10.x86_64",
        "console": "ttyS0,115200n8",
        "crashkernel": "1G-4G:192M,4G-64G:256M,64G-:512M",
        "no_timer_check": true,
        "ro": true,
        "root": "UUID=6b954e15-c908-4267-af94-914517f663e0"
    },
    "processor": [
        "0",
        "AuthenticAMD",
        "AMD EPYC-Milan Processor"
    ],
    "processor_cores": 1,
    "processor_count": 1,
    "processor_nproc": 1,
    "processor_threads_per_core": 1,
    "processor_vcpus": 1,
    "product_name": "None",
    "product_serial": "NA",
    "product_uuid": "NA",
    "product_version": "RHEL-9.4.0 PC (Q35 + ICH9, 2009)",
    "python": {
        "executable": "/usr/bin/python3",
        "has_sslcontext": true,
        "type": "cpython",
        "version": {
            "major": 3,
            "micro": 8,
            "minor": 12,
            "releaselevel": "final",
            "serial": 0
        },
        "version_info": [
            3,
            12,
            8,
            "final",
            0
        ]
    },
    "python_version": "3.12.8",
    "real_group_id": 1000,
    "real_user_id": 1000,
    "selinux": {
        "config_mode": "enforcing",
        "mode": "enforcing",
        "policyvers": 33,
        "status": "enabled",
        "type": "targeted"
    },
    "selinux_python_present": true,
    "service_mgr": "systemd",
    "ssh_host_key_ecdsa_public": "AAAAE2VjZHNhLXNoYTItbmlzdHAyNTYAAAAIbmlzdHAyNTYAAABBBMEXOPR0dBsMfroWyEIXIkkGX4WaGveAjXyrAYss2ixbb3cPFYM5qdlGI12ZPnRgOxC6/3fSrTu/rR8uuTHRisE=",
    "ssh_host_key_ecdsa_public_keytype": "ecdsa-sha2-nistp256",
    "ssh_host_key_ed25519_public": "AAAAC3NzaC1lZDI1NTE5AAAAICz+hkwYNh8QAGEg7yem4O28B/Po05piyhDbjUxFP/vy",
    "ssh_host_key_ed25519_public_keytype": "ssh-ed25519",
    "ssh_host_key_rsa_public": "AAAAB3NzaC1yc2EAAAADAQABAAABgQCWEtd8cnvvcEXCfiLXvOm85bAKPkTOuxze++ejAb1zF8yGmcHcE83i3VyIJlSnfFyPZh0kV8g8ZBV8TOvlz32R3d3wQggsXS6xT+lkkhokVODyc0JLsEl0mN24HGxacHu64hvLoIgQ5kjLjA3cqXhKfP0IdzlLgzJlFz7OZz6aBZDcRxWHEYQNZfOOCNSPUKpNPX2r1Fje5X6bIXgkzITV5aeREXqsYsukdKG8eERgfEFOWEhMIOq6vI2W5DCVD5F3rechSi8LLP43FtSse3RK/xLXJLvsEdavyK12MCWUPMYz9xQx/dbG2d/ytIrx/YsaQN3qmPvBvggztjOjEdSCbCfVZ27OL/NNzgwfRc26DiqSK0roF9UGum7+YLw8hRqTqI2X3vi7A0RAF6BUgNKQuGhRqdoOgYl7YQd3L42mOlhjfxRAhJDJWrQNRwPP+O5QWz9epaYuc7IqyICkKvoUk+C6+mWLvRB3q3Cyv+Bu/pl1gKuD58ZnCehYoYJMRUE=",
    "ssh_host_key_rsa_public_keytype": "ssh-rsa",
    "swapfree_mb": 0,
    "swaptotal_mb": 0,
    "system": "Linux",
    "system_capabilities": [
        ""
    ],
    "system_capabilities_enforced": "True",
    "system_vendor": "KubeVirt",
    "uptime_seconds": 42,
    "user_dir": "/home/molecule",
    "user_gecos": "",
    "user_gid": 1000,
    "user_id": "molecule",
    "user_shell": "/bin/bash",
    "user_uid": 1000,
    "userspace_architecture": "x86_64",
    "userspace_bits": "64",
    "virtualization_role": "guest",
    "virtualization_tech_guest": [
        "KubeVirt"
    ],
    "virtualization_tech_host": [],
    "virtualization_type": "KubeVirt"
}